hlsscraper/__init__.py
hlsscraper/locators/__init__.py
hlsscraper/locators/article.py
hlsscraper/locators/family.py
hlsscraper/locators/open_data.py
hlsscraper/locators/person.py
hlsscraper/locators/place.py
hlsscraper/pages/__init__.py
hlsscraper/pages/article.py
hlsscraper/pages/family.py
hlsscraper/pages/logging_utils.py
hlsscraper/pages/open_data.py
hlsscraper/pages/person.py
hlsscraper/pages/place.py
hlsscraper/scraper.py
hlsscraper-0.0.1.dist-info/LICENSE
hlsscraper-0.0.1.dist-info/WHEEL
hlsscraper-0.0.1.dist-info/METADATA
hlsscraper-0.0.1.dist-info/RECORD
