Metadata-Version: 2.1
Name: hlsscraper
Version: 0.0.1
Summary: 
Author: Jorit Studer
Author-email: jorit.studer@gmail.com
Requires-Python: >=3.9,<4.0
Classifier: Programming Language :: Python :: 3
Classifier: Programming Language :: Python :: 3.9
Classifier: Programming Language :: Python :: 3.10
Classifier: Programming Language :: Python :: 3.11
Requires-Dist: MechanicalSoup (>=1.2.0,<2.0.0)
Requires-Dist: pandas (>=1.5,<2.0)
